{"is_source_file": true, "format": "JavaScript (React JSX)", "description": "This file defines a React functional component named Sidebar which manages and displays categories with the ability to add and delete categories, including handling interactions and state management.", "external_files": [], "external_methods": ["React", "useState", "useEffect"], "published": ["default"], "classes": [], "methods": [{"name": "Sidebar({ selectedCategory, setSelectedCategory })", "description": "Main React component rendering a sidebar for category management, including handling adding and deleting categories.", "scope": "", "scopeKind": ""}, {"name": "handleAdd", "description": "Handles adding a new category to the list, preventing duplicates and empty strings."}, {"name": "handleDelete", "description": "Handles deleting a category, with confirmation and special handling if the deleted category is currently selected."}], "calls": ["setCategories", "setNewCategory", "categories.includes", "categories.filter", "window.confirm", "setSelectedCategory"], "search-terms": ["React component", "category management", "Sidebar JSX", "add category", "delete category", "category list", "useState hooks"], "state": 2, "file_id": 14, "knowledge_revision": 29, "git_revision": "", "ctags": [{"_type": "tag", "name": "24", "path": "/home/kavia/workspace/code-generation/personal-notes-organizer-147311-147321/notes_frontend/src/components/Sidebar.jsx", "pattern": "/^          maxLength={24}$/", "language": "JavaScript", "kind": "field", "scope": "Sidebar.maxLength", "scopeKind": "class"}, {"_type": "tag", "name": "Sidebar", "path": "/home/kavia/workspace/code-generation/personal-notes-organizer-147311-147321/notes_frontend/src/components/Sidebar.jsx", "pattern": "/^export default function Sidebar({ selectedCategory, setSelectedCategory }) {$/", "language": "JavaScript", "kind": "function", "signature": "({ selectedCategory, setSelectedCategory })"}, {"_type": "tag", "name": "defaultCategories", "path": "/home/kavia/workspace/code-generation/personal-notes-organizer-147311-147321/notes_frontend/src/components/Sidebar.jsx", "pattern": "/^const defaultCategories = [\"All\", \"Personal\", \"Work\", \"Ideas\"];$/", "language": "JavaScript", "kind": "constant"}, {"_type": "tag", "name": "newCategory", "path": "/home/kavia/workspace/code-generation/personal-notes-organizer-147311-147321/notes_frontend/src/components/Sidebar.jsx", "pattern": "/^          value={newCategory}$/", "language": "JavaScript", "kind": "field", "scope": "Sidebar.value", "scopeKind": "class"}], "hash": "4797f744e00fb3f174f796c175d4f840", "format-version": 4, "code-base-name": "notes_frontend", "filename": "notes_frontend/src/components/Sidebar.jsx", "fields": [{"name": "maxLength={24}", "scope": "Sidebar.maxLength", "scopeKind": "class", "description": "unavailable"}, {"name": "value={newCategory}", "scope": "Sidebar.value", "scopeKind": "class", "description": "unavailable"}], "revision_history": [{"29": ""}]}